{
    "key": "group_5b9f6971c882d",
    "title": "Categories",
    "fields": [
        {
            "key": "field_57cd8fd353c90",
            "label": "Category Image",
            "name": "category_image",
            "type": "image",
            "instructions": "",
            "required": 0,
            "conditional_logic": 0,
            "wrapper": {
                "width": "",
                "class": "",
                "id": ""
            },
            "return_format": "array",
            "preview_size": "full",
            "library": "all",
            "min_width": "",
            "min_height": "",
            "min_size": "",
            "max_width": "",
            "max_height": "",
            "max_size": "",
            "mime_types": "",
            "translations": "copy_once"
        },
        {
            "key": "field_57d02ffbda86f",
            "label": "Category Style",
            "name": "category_style",
            "type": "select",
            "instructions": "",
            "required": 0,
            "conditional_logic": 0,
            "wrapper": {
                "width": "",
                "class": "",
                "id": ""
            },
            "choices": {
                "kids": "kids",
                "teachers": "teachers",
                "grown-ups": "grown-ups"
            },
            "default_value": false,
            "allow_null": 0,
            "multiple": 0,
            "ui": 0,
            "ajax": 0,
            "placeholder": "",
            "return_format": "value"
        }
    ],
    "location": [
        [
            {
                "param": "taxonomy",
                "operator": "==",
                "value": "category"
            }
        ]
    ],
    "menu_order": 0,
    "position": "normal",
    "style": "seamless",
    "label_placement": "top",
    "instruction_placement": "label",
    "hide_on_screen": "",
    "active": true,
    "description": "",
    "modified": 1635148282
}